comfy_executors/__init__.py
comfy_executors/constants.py
comfy_executors/executors.py
comfy_executors/mixins.py
comfy_executors/utils.py
comfy_executors/workflows.py
comfy_executors-0.1.0.dist-info/METADATA
comfy_executors-0.1.0.dist-info/WHEEL
comfy_executors-0.1.0.dist-info/RECORD
