Metadata-Version: 2.1
Name: comfy-executors
Version: 0.1.0
Summary: 
Author: Kristian Klemon
Author-email: kristian.klemon@gmail.com
Requires-Python: >=3.10,<4.0
Classifier: Programming Language :: Python :: 3
Classifier: Programming Language :: Python :: 3.10
Classifier: Programming Language :: Python :: 3.11
Classifier: Programming Language :: Python :: 3.12
Requires-Dist: aiostream (<0.6.0)
Requires-Dist: comfy-api-client (>=0.1.0,<0.2.0)
Requires-Dist: jinja2 (>=3.1.3,<4.0.0)
Requires-Dist: pillow (>=10.3.0,<11.0.0)
Requires-Dist: requests (>=2.31.0,<3.0.0)
Requires-Dist: runpod (>=1.6.2,<2.0.0)
